araste/__init__.py
araste/char_maps.py
araste/filters.py
araste/fonts/3d.aff
araste/fonts/aheste.aff
araste/fonts/aipara.aff
araste/fonts/aipara_mini.aff
araste/fonts/danial.aff
araste/fonts/dastkhat.aff
araste/fonts/khodkar.aff
araste/fonts/naqshe.aff
araste/fonts/nima.aff
araste/fonts/sangi.aff
araste/fonts/sangi_mini.aff
araste/fonts/zivar.aff
araste-3.3.data/scripts/araste
araste-3.3.data/scripts/araste-get
araste-3.3.dist-info/LICENSE
araste-3.3.dist-info/METADATA
araste-3.3.dist-info/WHEEL
araste-3.3.dist-info/top_level.txt
araste-3.3.dist-info/RECORD
