Metadata-Version: 2.1
Name: araste
Version: 3.3
Summary: Convert persian text to ascii art
Home-page: https://github.com/ekm507/araste
Author: Erfan Kheirollahi
Author-email: ekm507@gmail.com
Keywords: figlet
License-File: LICENSE
Requires-Dist: requests
